ei_glossary/__init__.py
ei_glossary/core.py
ei_glossary/utils.py
ei_glossary-0.0.1.dist-info/LICENSE
ei_glossary-0.0.1.dist-info/METADATA
ei_glossary-0.0.1.dist-info/WHEEL
ei_glossary-0.0.1.dist-info/top_level.txt
ei_glossary-0.0.1.dist-info/RECORD
