Metadata-Version: 2.1
Name: ei-glossary
Version: 0.0.1
Summary: Client library for ecoinvent glossary
Author-email: Chris Mutel <mutel@ecoinvent.org>
Maintainer-email: Chris Mutel <mutel@ecoinvent.org>
Project-URL: source, https://github.com/ecoinvent/ei_glossary
Project-URL: homepage, https://github.com/ecoinvent/ei_glossary
Project-URL: tracker, https://github.com/ecoinvent/ei_glossary/issues
Classifier: Development Status :: 4 - Beta
Classifier: Programming Language :: Python
Classifier: Programming Language :: Python :: 3
Classifier: Programming Language :: Python :: 3.9
Classifier: Programming Language :: Python :: 3.10
Classifier: Programming Language :: Python :: 3.11
Classifier: Programming Language :: Python :: 3.12
Classifier: Natural Language :: English
Classifier: Operating System :: OS Independent
Classifier: Topic :: Scientific/Engineering
Requires-Python: >=3.10
License-File: LICENSE
Requires-Dist: Levenshtein
Requires-Dist: pandas
Requires-Dist: requests
Provides-Extra: dev
Requires-Dist: build ; extra == 'dev'
Requires-Dist: pre-commit ; extra == 'dev'
Requires-Dist: pylint ; extra == 'dev'
Requires-Dist: pytest ; extra == 'dev'
Requires-Dist: pytest-cov ; extra == 'dev'
Requires-Dist: setuptools ; extra == 'dev'
Provides-Extra: testing
Requires-Dist: ei-glossary ; extra == 'testing'
Requires-Dist: pytest ; extra == 'testing'
Requires-Dist: pytest-cov ; extra == 'testing'
Requires-Dist: python-coveralls ; extra == 'testing'
